{"15069625": {"Category": ["化學", "其他", "食品", "飼料"], "SubCate": {"其他批發": ["其他商品經紀"], "食品批發": ["調味料（辛、香料除外）批發"], "動物飼料批發": ["動物飼料批發"], "化學批發": ["其他化學原料批發"]}, "Risk": "2", "ComName": "友源貿易股份有限公司", "Amount": "3311.3600000", "Uninum": "15069625", "Capital": 20000.0}, "72175181": {"Category": ["化學", "藥品", "食品"], "SubCate": {"藥品製造": ["中藥製造", "人用西藥製造"], "食品製造": ["特殊營養食品製造"], "化學製造": ["其他化粧品製造"]}, "Risk": "1", "ComName": "新喜國際企業股份有限公司", "Amount": "0.0009058", "Uninum": "72175181", "Capital": 2800.0}, "51006301": {"Category": ["藥品", "食品"], "SubCate": {"藥品製造": ["人用西藥製造"], "食品製造": ["特殊營養食品製造"], "藥品批發": ["西藥批發"]}, "Risk": "1", "ComName": "十全實業股份有限公司", "Amount": "0.0245519", "Uninum": "51006301", "Capital": 10880.0}, "85610030": {"Category": ["化學", "藥品"], "SubCate": {"藥品製造": ["人用西藥製造"], "化學製造": ["其他化粧品製造"]}, "Risk": "1", "ComName": "美西製藥有限公司", "Amount": "0.0032875", "Uninum": "85610030", "Capital": 1500.0}, "29084393": {"Category": ["食品"], "SubCate": {"食品製造": ["其他未分類食品製造"], "食品批發": ["未分類其他食品批發"]}, "Risk": "1", "ComName": "鴻仲生物科技有限公司", "Amount": "0.0130420", "Uninum": "29084393", "Capital": 1740.0}, "12632261": {"Category": ["藥品", "飼料", "食品", "農產"], "SubCate": {"食品製造": ["特殊營養食品製造"], "藥品批發": ["西藥批發"], "動物飼料批發": ["動物飼料批發"], "農產栽培": ["食用菌菇類菌種培育"]}, "Risk": "2", "ComName": "得榮生物科技股份有限公司", "Amount": "0.0009500", "Uninum": "12632261", "Capital": 22280.0}, "89884975": {"Category": ["化學", "藥品", "飲料", "食品"], "SubCate": {"藥品製造": ["中藥製造"], "食品製造": ["其他未分類食品製造"], "飲料製造": ["機能性飲料製造"], "化學製造": ["清潔劑製造"]}, "Risk": "2", "ComName": "三友生技醫藥股份有限公司", "Amount": "0.0093032", "Uninum": "89884975", "Capital": 15530.0}, "16653688": {"Category": ["藥品"], "SubCate": {"藥品批發": ["醫療耗材批發"]}, "Risk": "3", "ComName": "華星生物科技股份有限公司", "Amount": "0.0053200", "Uninum": "16653688", "Capital": 35000.0}, "11145904": {"Category": ["其他"], "SubCate": {"其他製造": ["航空器及其零件製造"], "其他產業": ["飛機出租", "航空運輸", "航空器維修"]}, "Risk": "2", "ComName": "中華航空股份有限公司", "Amount": "337.8089000", "Uninum": "11145904", "Capital": 5200000.0}, "04293133": {"Category": ["化學", "其他"], "SubCate": {"其他製造": ["其他石油及煤製品製造"], "化學製造": ["未分類其他化學製品製造", "染料及顏料製造", "其他合成樹脂及塑膠製造"]}, "Risk": "1", "ComName": "員和工業股份有限公司", "Amount": "3167.9174020", "Uninum": "04293133", "Capital": 50000.0}, "11912601": {"Category": ["其他"], "SubCate": {"其他批發": ["綜合商品批發", "其他商品經紀"]}, "Risk": "1", "ComName": "輝瑞生技股份有限公司", "Amount": "0.1209243", "Uninum": "11912601", "Capital": 62000.0}, "83606692": {"Category": ["食品"], "SubCate": {"食品製造": ["冷凍調理蔬果製造", "冷凍調理水產品製造"]}, "Risk": "1", "ComName": "永昇冷凍食品工業股份有限公司", "Amount": "0.7171000", "Uninum": "83606692", "Capital": 18180.0}, "84171822": {"Category": ["化學", "食品"], "SubCate": {"食品批發": ["未分類其他食品批發"], "化學批發": ["其他化學製品批發"]}, "Risk": "2", "ComName": "欣欣化學有限公司", "Amount": "1.2224719", "Uninum": "84171822", "Capital": 500.0}, "71122503": {"Category": ["藥品", "其他", "食品"], "SubCate": {"藥品製造": ["動物用西藥製造", "人用西藥製造"], "食品製造": ["其他未分類食品製造"], "其他批發": ["醫療機械設備批發"]}, "Risk": "3", "ComName": "生達化學製藥股份有限公司", "Amount": "5.6726391", "Uninum": "71122503", "Capital": 178696.0}, "56112203": {"Category": ["化學", "藥品", "其他", "食品"], "SubCate": {"藥品製造": ["人用西藥製造"], "食品製造": ["果凍製造"], "其他批發": ["其他化粧品批發"], "化學製造": ["其他化粧品製造"]}, "Risk": "1", "ComName": "利達製藥股份有限公司", "Amount": "0.0078085", "Uninum": "56112203", "Capital": 5000.0}, "18916906": {"Category": ["藥品"], "SubCate": {"藥品製造": ["中藥製造", "中藥製造"], "藥品零售": ["中藥零售", "中藥零售"]}, "Risk": "2", "ComName": "順天堂藥廠股份有限公司", "Amount": "0.0002970", "Uninum": "18916906", "Capital": 44100.0}, "35127383": {"Category": ["藥品"], "SubCate": {"藥品製造": ["人用西藥製造"]}, "Risk": "1", "ComName": "回春堂製藥廠股份有限公司", "Amount": "0.0054935", "Uninum": "35127383", "Capital": 5000.0}, "22397048": {"Category": ["化學", "藥品"], "SubCate": {"藥品製造": ["中藥製造", "動物用西藥製造"], "化學製造": ["未分類其他化學製品製造", "其他化粧品製造"]}, "Risk": "2", "ComName": "南都化學製藥股份有限公司", "Amount": "0.0002180", "Uninum": "22397048", "Capital": 1000.0}, "28191640": {"Category": ["藥品", "其他"], "SubCate": {"藥品製造": ["生物藥品製造"], "其他產業": ["其他未分類專業、科學及技術服務"]}, "Risk": "3", "ComName": "汎球生物藥劑研發股份有限公司", "Amount": "0.0127050", "Uninum": "28191640", "Capital": 20850.0}, "69546202": {"Category": ["化學", "其他"], "SubCate": {"其他製造": ["未分類其他塑膠製品製造"], "其他批發": ["其他未分類專賣批發"], "化學製造": ["環境用藥製造", "農藥製造"]}, "Risk": "2", "ComName": "惠光股份有限公司", "Amount": "0.0059962", "Uninum": "69546202", "Capital": 80000.0}, "03563307": {"Category": ["其他", "食品", "農產"], "SubCate": {"食品製造": ["特殊營養食品製造"], "其他批發": ["其他化粧品批發", "其他商品經紀"], "農產栽培": ["未分類其他畜牧"]}, "Risk": "3", "ComName": "臺灣綠藻工業股份有限公司", "Amount": "0.0065039", "Uninum": "03563307", "Capital": 26565.0}, "97390356": {"Category": ["食品", "農產"], "SubCate": {"食品零售": ["豆類、麥類及其他雜糧零售"], "農產批發": ["稻米批發"], "食品製造": ["代客碾穀"]}, "Risk": "3", "ComName": "五王糧食股份有限公司", "Amount": "0.1150500", "Uninum": "97390356", "Capital": 21200.0}, "29108260": {"Category": ["化學", "藥品", "其他", "飼料"], "SubCate": {"其他批發": ["其他清潔用品批發"], "藥品批發": ["西藥批發"], "動物飼料批發": ["動物飼料批發"], "化學批發": ["其他化學原料批發"]}, "Risk": "1", "ComName": "合一生技股份有限公司", "Amount": "0.6515670", "Uninum": "29108260", "Capital": 193767.0}, "30950745": {"Category": ["藥品", "食品"], "SubCate": {"藥品製造": ["人用西藥製造"], "食品製造": ["特殊營養食品製造"], "食品批發": ["保健食品批發"], "食品零售": ["保健食品零售"]}, "Risk": "1", "ComName": "衛達化學製藥股份有限公司", "Amount": "82.2787447", "Uninum": "30950745", "Capital": 13500.0}, "22100398": {"Category": ["其他"], "SubCate": {"其他製造": ["電子及半導體生產用機械設備製造", "顯示器製造", "其他未分類電子零組件製造", "電子管製造"]}, "Risk": "3", "ComName": "勝華科技股份有限公司", "Amount": "0.0017900", "Uninum": "22100398", "Capital": 2047778.0}, "04610454": {"Category": ["藥品", "食品"], "SubCate": {"食品批發": ["保健食品批發"], "藥品零售": ["西藥零售"], "食品製造": ["食品罐頭（肉類、水產、蔬果罐頭除外）製造"]}, "Risk": "2", "ComName": "順華藥品工業股份有限公司", "Amount": "4.3732539", "Uninum": "04610454", "Capital": 2900.0}, "29184631": {"Category": ["食品", "農產"], "SubCate": {"食品製造": ["其他未分類食品製造"], "食品批發": ["未分類其他食品批發"], "農產栽培": ["其他食用菌菇類栽培"], "食品零售": ["未分類其他食品及飲料、菸草製品零售"]}, "Risk": "2", "ComName": "喬本生醫股份有限公司", "Amount": "0.0065752", "Uninum": "29184631", "Capital": 35710.0}, "23526610": {"Category": ["化學", "藥品", "其他"], "SubCate": {"其他批發": ["實驗設備批發"], "藥品批發": ["西藥批發"], "化學批發": ["化學溶劑、工業添加劑批發", "其他化學原料批發"]}, "Risk": "2", "ComName": "台灣默克股份有限公司", "Amount": "574.1754490", "Uninum": "23526610", "Capital": 10000.0}, "80177887": {"Category": ["化學", "藥品", "其他"], "SubCate": {"藥品其他": ["營養諮詢機構"], "其他批發": ["實驗設備批發"], "其他產業": ["未分類其他技術檢測及分析服務"], "化學製造": ["其他化粧品製造"]}, "Risk": "2", "ComName": "聯群生技有限公司", "Amount": "0.0000900", "Uninum": "80177887", "Capital": 2200.0}, "68531103": {"Category": ["藥品", "食品"], "SubCate": {"藥品製造": ["人用西藥製造"], "食品製造": ["特殊營養食品製造"]}, "Risk": "1", "ComName": "信隆藥品工業股份有限公司", "Amount": "1.2581734", "Uninum": "68531103", "Capital": 1000.0}, "56065601": {"Category": ["藥品", "其他", "食品"], "SubCate": {"藥品製造": ["動物用西藥製造", "人用西藥製造"], "食品製造": ["特殊營養食品製造"], "其他零售": ["電視購物、網路購物"]}, "Risk": "2", "ComName": "永信藥品工業股份有限公司", "Amount": "16.5675375", "Uninum": "56065601", "Capital": 153736.0}, "84919193": {"Category": ["藥品", "其他"], "SubCate": {"其他批發": ["其他清潔用品批發"], "其他產業": ["其他未分類專業、科學及技術服務", "其他管理顧問服務"], "藥品批發": ["醫療耗材批發"]}, "Risk": "1", "ComName": "瀚仕生醫科技股份有限公司", "Amount": "0.0788000", "Uninum": "84919193", "Capital": 5200.0}, "11214704": {"Category": ["藥品"], "SubCate": {"藥品製造": ["人用西藥製造"]}, "Risk": "3", "ComName": "尼斯可股份有限公司新莊廠", "Amount": "0.0006650", "Uninum": "11214704", "Capital": 3500.0}, "80259156": {"Category": ["藥品", "其他"], "SubCate": {"其他批發": ["其他商品經紀"], "藥品批發": ["醫療耗材批發", "西藥批發", "中藥批發"]}, "Risk": "3", "ComName": "盈盈生技製藥股份有限公司", "Amount": "0.0025611", "Uninum": "80259156", "Capital": 13000.0}, "30853589": {"Category": ["化學", "藥品", "食品"], "SubCate": {"藥品製造": ["中藥製造", "人用西藥製造"], "食品零售": ["未分類其他食品及飲料、菸草製品零售"], "化學製造": ["其他化粧品製造"]}, "Risk": "2", "ComName": "永勝藥品工業股份有限公司", "Amount": "26.3668805", "Uninum": "30853589", "Capital": 7500.0}, "12738546": {"Category": ["藥品"], "SubCate": {"藥品批發": ["動物藥品批發", "西藥批發"]}, "Risk": "1", "ComName": "麥迪森企業股份有限公司", "Amount": "0.0004845", "Uninum": "12738546", "Capital": 10250.0}, "59039712": {"Category": ["藥品"], "SubCate": {"藥品製造": ["人用西藥製造"]}, "Risk": "2", "ComName": "久松化學企業股份有限公司", "Amount": "0.0027531", "Uninum": "59039712", "Capital": 2000.0}, "53942917": {"Category": ["食品"], "SubCate": {"食品批發": ["保健食品批發"]}, "Risk": "2", "ComName": "康立為生醫科技股份有限公司", "Amount": "0.0106400", "Uninum": "53942917", "Capital": 8640.0}, "80170651": {"Category": ["化學", "其他"], "SubCate": {"其他批發": ["其他商品經紀"], "化學製造": ["石油化工原料製造"], "化學批發": ["染料、顏料批發", "其他化學原料批發"]}, "Risk": "2", "ComName": "三福化工股份有限公司", "Amount": "0.0227470", "Uninum": "80170651", "Capital": 88000.0}, "86218169": {"Category": ["化學", "其他"], "SubCate": {"其他製造": ["未分類其他工業製品製造"], "其他批發": ["實驗設備批發"], "化學批發": ["其他化學製品批發"]}, "Risk": "1", "ComName": "方強企業有限公司", "Amount": "3.7838500", "Uninum": "86218169", "Capital": 5000.0}, "03522600": {"Category": ["其他"], "SubCate": {"其他產業": ["聚酯纖維梭織布製造", "棉混紡梭織布製造"]}, "Risk": "3", "ComName": "遠東新世紀股份有限公司", "Amount": "0.0319900", "Uninum": "03522600", "Capital": 5352875.0}, "63129193": {"Category": ["藥品"], "SubCate": {"藥品製造": ["人用西藥製造"]}, "Risk": "2", "ComName": "政德製藥股份有限公司", "Amount": "0.0231221", "Uninum": "63129193", "Capital": 15000.0}, "03379409": {"Category": ["化學", "其他"], "SubCate": {"其他產業": ["其他未分類專業、科學及技術服務", "其他最後修整工程"], "化學製造": ["塗料製造", "聚酯粒製造"]}, "Risk": "1", "ComName": "國森企業股份有限公司", "Amount": "161.7296800", "Uninum": "03379409", "Capital": 8500.0}, "15458455": {"Category": ["化學", "藥品"], "SubCate": {"藥品製造": ["動物用西藥製造", "原料藥製造"], "化學製造": ["染料及顏料製造"]}, "Risk": "2", "ComName": "臺灣永光化學工業股份有限公司", "Amount": "24.5092423", "Uninum": "15458455", "Capital": 521668.0}, "68770700": {"Category": ["藥品"], "SubCate": {"藥品製造": ["動物用西藥製造"], "藥品零售": ["西藥零售"], "藥品批發": ["動物藥品批發", "西藥批發"]}, "Risk": "2", "ComName": "瑞士藥廠股份有限公司", "Amount": "0.0409943", "Uninum": "68770700", "Capital": 15600.0}, "07407503": {"Category": ["藥品"], "SubCate": {"藥品製造": ["人用西藥製造"]}, "Risk": "1", "ComName": "華盛頓製藥廠股份有限公司", "Amount": "0.0031912", "Uninum": "07407503", "Capital": 5000.0}, "75064259": {"Category": ["藥品", "食品"], "SubCate": {"藥品製造": ["中藥製造", "人用西藥製造"], "食品製造": ["特殊營養食品製造"]}, "Risk": "1", "ComName": "井田製藥工業股份有限公司", "Amount": "0.4836240", "Uninum": "75064259", "Capital": 8000.0}, "22357854": {"Category": ["化學", "其他"], "SubCate": {"其他產業": ["自然及工程科學研究發展服務"], "化學製造": ["其他化粧品製造"]}, "Risk": "3", "ComName": "新鈺生技股份有限公司", "Amount": "30.5180000", "Uninum": "22357854", "Capital": 7500.0}, "28708250": {"Category": ["化學", "農產"], "SubCate": {"農產栽培": ["其他食用菌菇類栽培"], "化學製造": ["未分類其他化學製品製造"]}, "Risk": "2", "ComName": "晨暉生物科技股份有限公司", "Amount": "0.2013600", "Uninum": "28708250", "Capital": 24593.0}, "04742997": {"Category": ["藥品", "其他"], "SubCate": {"藥品製造": ["人用西藥製造"], "藥品零售": ["西藥零售"], "其他產業": ["其他非金融性無形資產租賃"], "藥品批發": ["西藥批發"]}, "Risk": "1", "ComName": "寶齡富錦生技股份有限公司", "Amount": "0.0579952", "Uninum": "04742997", "Capital": 56215.0}, "73251209": {"Category": ["其他", "食品", "飼料"], "SubCate": {"食品製造": ["其他未分類食品製造", "速食麵條、粉條製造"], "其他製造": ["未分類其他工業製品製造"], "動物飼料製造": ["動物飼料配製"]}, "Risk": "2", "ComName": "統一企業股份有限公司", "Amount": "0.0003515", "Uninum": "73251209", "Capital": 5682015.0}, "22002761": {"Category": ["藥品"], "SubCate": {"藥品製造": ["人用西藥製造"]}, "Risk": "1", "ComName": "仁興化學製藥股份有限公司", "Amount": "0.0040060", "Uninum": "22002761", "Capital": 5250.0}, "86662605": {"Category": ["其他", "食品"], "SubCate": {"其他製造": ["未分類其他光學儀器及設備製造"], "食品其他": ["農、林、漁、礦、食品、紡織等技術指導服務"]}, "Risk": "1", "ComName": "昭信標準檢驗股份有限公司", "Amount": "0.0005020", "Uninum": "86662605", "Capital": 2200.0}, "83748073": {"Category": ["化學", "藥品", "其他"], "SubCate": {"藥品製造": ["人用西藥製造"], "其他製造": ["其他醫療器材及用品製造"], "化學製造": ["其他化粧品製造"]}, "Risk": "2", "ComName": "臺灣派頓化學製藥股份有限公司", "Amount": "0.1117634", "Uninum": "83748073", "Capital": 8500.0}, "11821341": {"Category": ["化學", "藥品"], "SubCate": {"藥品製造": ["人用西藥製造"], "化學製造": ["其他化粧品製造"]}, "Risk": "3", "ComName": "台灣東洋藥品工業股份有限公司", "Amount": "59.6665081", "Uninum": "11821341", "Capital": 248649.0}, "65534366": {"Category": ["其他", "食品", "飲料"], "SubCate": {"食品製造": ["蔬果罐頭製造"], "飲料製造": ["蔬果汁製造"], "其他零售": ["其他化粧品零售"], "食品零售": ["醃漬水產品零售"]}, "Risk": "1", "ComName": "愛之味股份有限公司嘉義食品廠", "Amount": "0.0070521", "Uninum": "65534366", "Capital": 497689.0}, "86973523": {"Category": ["化學", "食品", "飼料"], "SubCate": {"食品製造": ["其他未分類食品製造"], "食品批發": ["未分類其他食品批發"], "動物飼料批發": ["動物飼料批發"], "化學製造": ["其他化粧品製造"]}, "Risk": "2", "ComName": "麗豐實業股份有限公司", "Amount": "0.0397930", "Uninum": "86973523", "Capital": 5000.0}, "60291381": {"Category": ["藥品"], "SubCate": {"藥品製造": ["中藥製造", "人用西藥製造"]}, "Risk": "1", "ComName": "吉立製藥股份有限公司", "Amount": "0.5240000", "Uninum": "60291381", "Capital": 1554.0}, "35348007": {"Category": ["藥品", "食品"], "SubCate": {"藥品製造": ["人用西藥製造"], "食品零售": ["保健食品零售"], "食品批發": ["保健食品批發"], "藥品批發": ["西藥批發"]}, "Risk": "2", "ComName": "強生化學製藥廠股份有限公司", "Amount": "10.9674390", "Uninum": "35348007", "Capital": 30018.0}, "96922622": {"Category": ["化學", "藥品"], "SubCate": {"藥品製造": ["動物用西藥製造", "人用西藥製造"], "藥品其他": ["醫學檢驗服務"], "化學製造": ["其他化粧品製造"]}, "Risk": "1", "ComName": "台耀化學股份有限公司", "Amount": "163.1370933", "Uninum": "96922622", "Capital": 85137.0}, "59036721": {"Category": ["藥品", "其他"], "SubCate": {"藥品製造": ["人用西藥製造"], "其他批發": ["其他清潔用品批發"]}, "Risk": "3", "ComName": "大豐製藥股份有限公司", "Amount": "1.1414420", "Uninum": "59036721", "Capital": 12000.0}, "22662828": {"Category": ["藥品", "其他"], "SubCate": {"其他批發": ["醫療機械設備批發", "其他化粧品批發", "醫療機械設備批發", "其他化粧品批發"], "藥品批發": ["動物藥品批發", "西藥批發", "動物藥品批發", "西藥批發"]}, "Risk": "2", "ComName": "佐藤製藥股份有限公司新竹廠", "Amount": "0.0002420", "Uninum": "22662828", "Capital": 12000.0}, "21242638": {"Category": ["化學", "其他"], "SubCate": {"其他批發": ["綜合商品批發", "綜合商品批發"], "化學製造": ["其他基本化學材料製造", "其他基本化學材料製造"]}, "Risk": "1", "ComName": "台灣陶氏化學股份有限公司", "Amount": "0.0001250", "Uninum": "21242638", "Capital": 20000.0}, "24430803": {"Category": ["藥品", "食品"], "SubCate": {"藥品製造": ["中藥製造", "人用西藥製造"], "食品製造": ["特殊營養食品製造"]}, "Risk": "1", "ComName": "井田國際醫藥廠股份有限公司", "Amount": "0.4183760", "Uninum": "24430803", "Capital": 20000.0}, "11456110": {"Category": ["藥品"], "SubCate": {"藥品製造": ["人用西藥製造"], "藥品零售": ["西藥零售"]}, "Risk": "1", "ComName": "美時化學製藥股份有限公司", "Amount": "0.0850560", "Uninum": "11456110", "Capital": 238491.0}, "35152903": {"Category": ["藥品"], "SubCate": {"藥品製造": ["人用西藥製造"]}, "Risk": "2", "ComName": "西德有機化學藥品股份有限公司", "Amount": "0.0041613", "Uninum": "35152903", "Capital": 15100.0}, "54368952": {"Category": ["藥品", "食品", "農產"], "SubCate": {"食品批發": ["未分類其他食品批發"], "農產栽培": ["其他農作物栽培"], "藥品批發": ["其他藥品及醫療用品零售"]}, "Risk": "3", "ComName": "健泉漾齡醫事檢驗所", "Amount": "0.0055062", "Uninum": "54368952", "Capital": 3000.0}, "14001297": {"Category": ["藥品", "其他"], "SubCate": {"藥品製造": ["人用西藥製造"], "其他批發": ["其他商品經紀"], "藥品零售": ["西藥零售"]}, "Risk": "3", "ComName": "台灣大塚製藥股份有限公司", "Amount": "0.0009419", "Uninum": "14001297", "Capital": 20000.0}, "13151374": {"Category": ["化學", "其他", "飼料"], "SubCate": {"其他批發": ["綜合商品批發"], "動物飼料製造": ["動物飼料配製"], "動物飼料批發": ["動物飼料批發"], "化學批發": ["肥料批發"]}, "Risk": "2", "ComName": "京冠生物科技股份有限公司", "Amount": "0.0119394", "Uninum": "13151374", "Capital": 9363.0}, "70555349": {"Category": ["藥品", "其他", "食品", "飲料"], "SubCate": {"食品製造": ["其他未分類食品製造"], "飲料製造": ["其他乳品製造"], "其他批發": ["其他化粧品批發"], "藥品批發": ["西藥批發"]}, "Risk": "1", "ComName": "中天生物科技股份有限公司", "Amount": "0.3340755", "Uninum": "70555349", "Capital": 425342.0}, "16207098": {"Category": ["藥品"], "SubCate": {"藥品製造": ["中藥製造"], "藥品批發": ["中藥批發"]}, "Risk": "1", "ComName": "全生製藥股份有限公司", "Amount": "0.0010300", "Uninum": "16207098", "Capital": 1000.0}, "27476083": {"Category": ["其他"], "SubCate": {"其他製造": ["橡膠及塑膠加工用機械設備製造", "塑膠袋製品製造"]}, "Risk": "1", "ComName": "旭源包裝科技股份有限公司嘉義分公司", "Amount": "0.5320000", "Uninum": "27476083", "Capital": 38502.0}, "51911712": {"Category": ["化學", "其他"], "SubCate": {"其他製造": ["其他醫療器材及用品製造"], "化學製造": ["農藥製造", "其他肥料製造", "其他基本化學材料製造"]}, "Risk": "2", "ComName": "興農股份有限公司", "Amount": "11.8742241", "Uninum": "51911712", "Capital": 344408.0}, "11768704": {"Category": ["其他", "食品", "飲料"], "SubCate": {"食品製造": ["其他糖果製造", "其他烘焙炊蒸食品製造"], "飲料製造": ["其他乳品製造"], "其他產業": ["未分類其他餐飲"]}, "Risk": "1", "ComName": "義美食品股份有限公司", "Amount": "0.0034355", "Uninum": "11768704", "Capital": 200000.0}, "28684877": {"Category": ["藥品", "其他"], "SubCate": {"藥品製造": ["人用西藥製造"], "其他批發": ["醫療機械設備批發", "量測設備批發"], "藥品批發": ["西藥批發"]}, "Risk": "2", "ComName": "保瑞藥業股份有限公司", "Amount": "0.0017251", "Uninum": "28684877", "Capital": 22450.0}, "52260152": {"Category": ["藥品", "其他"], "SubCate": {"藥品製造": ["人用西藥製造"], "其他批發": ["其他化粧品批發"]}, "Risk": "3", "ComName": "培力藥品工業股份有限公司", "Amount": "0.2992140", "Uninum": "52260152", "Capital": 15500.0}, "28059706": {"Category": ["化學", "藥品", "食品"], "SubCate": {"藥品製造": ["人用西藥製造"], "食品批發": ["未分類其他食品批發"], "藥品批發": ["西藥批發"], "化學製造": ["其他化粧品製造"]}, "Risk": "3", "ComName": "榮民製藥股份有限公司", "Amount": "8.8874043", "Uninum": "28059706", "Capital": 32000.0}, "12971536": {"Category": ["化學", "食品"], "SubCate": {"食品製造": ["其他未分類食品製造"], "食品批發": ["未分類其他食品批發"], "化學批發": ["其他化學製品批發"]}, "Risk": "3", "ComName": "立弘生化科技股份有限公司", "Amount": "302.5982250", "Uninum": "12971536", "Capital": 94600.0}, "54543375": {"Category": ["化學", "食品"], "SubCate": {"食品批發": ["保健食品批發"], "化學批發": ["其他化學製品批發", "其他化學原料批發"]}, "Risk": "3", "ComName": "永定科技有限公司", "Amount": "4.3039800", "Uninum": "54543375", "Capital": 200.0}, "23930512": {"Category": ["化學", "其他"], "SubCate": {"其他批發": ["未分類其他機械器具批發"], "其他產業": ["其他工程服務及相關技術顧問"], "化學批發": ["其他化學製品批發", "其他化學原料批發"]}, "Risk": "1", "ComName": "台灣巴斯夫股份有限公司", "Amount": "0.0913760", "Uninum": "23930512", "Capital": 37500.0}, "43211700": {"Category": ["藥品", "其他", "食品"], "SubCate": {"藥品製造": ["中藥製造", "人用西藥製造"], "食品製造": ["其他未分類食品製造"], "其他批發": ["其他商品經紀"]}, "Risk": "2", "ComName": "信東生技股份有限公司", "Amount": "20.0676690", "Uninum": "43211700", "Capital": 130223.0}, "22398004": {"Category": ["化學"], "SubCate": {"化學批發": ["其他化學製品批發"]}, "Risk": "1", "ComName": "新林化工原料有限公司", "Amount": "4.4200000", "Uninum": "22398004", "Capital": 300.0}, "73255839": {"Category": ["藥品", "食品"], "SubCate": {"藥品製造": ["中藥製造"], "食品製造": ["特殊營養食品製造"]}, "Risk": "2", "ComName": "港香蘭藥廠股份有限公司", "Amount": "0.0007967", "Uninum": "73255839", "Capital": 60000.0}, "11880517": {"Category": ["藥品", "其他", "飲料"], "SubCate": {"藥品製造": ["人用西藥製造"], "其他製造": ["其他醫療器材及用品製造"], "飲料製造": ["碳酸飲料製造"], "飲料零售": ["菸酒零售"]}, "Risk": "2", "ComName": "葡萄王生技股份有限公司", "Amount": "0.0731174", "Uninum": "11880517", "Capital": 130235.0}, "51390804": {"Category": ["化學", "藥品"], "SubCate": {"藥品製造": ["中藥製造", "人用西藥製造"], "化學製造": ["環境用藥製造"]}, "Risk": "2", "ComName": "明通化學製藥股份有限公司", "Amount": "0.0132510", "Uninum": "51390804", "Capital": 12000.0}, "83728956": {"Category": ["食品"], "SubCate": {"食品製造": ["其他食用油脂製造"]}, "Risk": "2", "ComName": "正義股份有限公司", "Amount": "0.0000053", "Uninum": "83728956", "Capital": 24000.0}, "15903054": {"Category": ["化學", "其他"], "SubCate": {"其他批發": ["其他商品經紀"], "化學批發": ["其他化學原料批發"]}, "Risk": "1", "ComName": "融鋒興業有限公司", "Amount": "0.4849275", "Uninum": "15903054", "Capital": 1500.0}, "96962861": {"Category": ["其他", "食品"], "SubCate": {"其他批發": ["醫療機械設備批發"], "食品批發": ["食用油脂批發", "畜肉批發"]}, "Risk": "3", "ComName": "歐美嘉股份有限公司", "Amount": "0.5221720", "Uninum": "96962861", "Capital": 10000.0}, "51652905": {"Category": ["藥品", "飲料"], "SubCate": {"藥品製造": ["人用西藥製造", "原料藥製造"], "飲料製造": ["其他非酒精飲料製造"]}, "Risk": "2", "ComName": "龍杏生技製藥股份有限公司", "Amount": "0.0024486", "Uninum": "51652905", "Capital": 5000.0}, "28589120": {"Category": ["其他", "食品"], "SubCate": {"食品製造": ["其他未分類食品製造"], "其他批發": ["其他商品經紀"]}, "Risk": "3", "ComName": "百歐仕科研股份有限公司", "Amount": "0.0028000", "Uninum": "28589120", "Capital": 6350.0}, "05007903": {"Category": ["飲料", "食品"], "SubCate": {"飲料製造": ["其他非酒精飲料製造", "其他非酒精飲料製造"], "食品批發": ["未分類其他食品批發", "調味料（辛、香料除外）批發", "未分類其他食品批發", "調味料（辛、香料除外）批發"], "飲料零售": ["乳製品（奶粉除外）零售", "乳製品（奶粉除外）零售"]}, "Risk": "2", "ComName": "金車股份有限公司", "Amount": "0.0006600", "Uninum": "05007903", "Capital": 405000.0}, "84268570": {"Category": ["化學"], "SubCate": {"化學批發": ["其他化學製品批發"]}, "Risk": "2", "ComName": "輔琳生化科技有限公司", "Amount": "16.1504800", "Uninum": "84268570", "Capital": 2000.0}, "71620635": {"Category": ["飲料", "食品", "農產"], "SubCate": {"食品製造": ["蔬果罐頭製造"], "飲料製造": ["其他非酒精飲料製造"], "食品批發": ["罐頭批發"], "農產栽培": ["其他農作物栽培"]}, "Risk": "2", "ComName": "臺灣可果美股份有限公司", "Amount": "0.0014520", "Uninum": "71620635", "Capital": 31635.0}, "72082135": {"Category": ["藥品", "其他", "食品"], "SubCate": {"藥品製造": ["人用西藥製造", "人用西藥製造"], "食品製造": ["特殊營養食品製造", "特殊營養食品製造"], "其他批發": ["其他未分類專賣批發", "其他未分類專賣批發"]}, "Risk": "2", "ComName": "溫士頓醫藥股份有限公司", "Amount": "0.0126210", "Uninum": "72082135", "Capital": 35000.0}, "66467822": {"Category": ["化學", "其他"], "SubCate": {"其他批發": ["未分類其他機械器具批發", "其他電子設備及其零組件批發"], "其他零售": ["家用光學產品零售"], "化學批發": ["其他化學原料批發"]}, "Risk": "2", "ComName": "弘力化工原料儀器有限公司", "Amount": "1.7516087", "Uninum": "66467822", "Capital": 820.0}, "14872195": {"Category": ["其他"], "SubCate": {"其他產業": ["其他廣告服務"], "其他零售": ["電腦及電腦週邊設備零售", "清潔用品零售"]}, "Risk": "2", "ComName": "勝德企業社", "Amount": "59.8850000", "Uninum": "14872195", "Capital": 24.0}, "70387977": {"Category": ["其他"], "SubCate": {"其他批發": ["電子器材、電子設備批發"]}, "Risk": "2", "ComName": "鴻元達業貿易有限公司", "Amount": "28.5831600", "Uninum": "70387977", "Capital": 1200.0}, "85748719": {"Category": ["藥品", "其他", "食品"], "SubCate": {"藥品製造": ["中藥製造"], "食品製造": ["特殊營養食品製造"], "其他產業": ["綜合研究發展服務"]}, "Risk": "1", "ComName": "莊松榮製藥廠有限公司", "Amount": "0.0597030", "Uninum": "85748719", "Capital": 10000.0}, "59016653": {"Category": ["化學", "藥品", "食品"], "SubCate": {"食品製造": ["其他未分類食品製造"], "藥品批發": ["其他藥品及醫療用品批發", "西藥批發"], "化學製造": ["其他化粧品製造"]}, "Risk": "3", "ComName": "富生化學製藥股份有限公司", "Amount": "0.1023310", "Uninum": "59016653", "Capital": 500.0}, "72004856": {"Category": ["藥品"], "SubCate": {"藥品製造": ["中藥製造", "人用西藥製造"]}, "Risk": "1", "ComName": "正和製藥股份有限公司", "Amount": "6.1926421", "Uninum": "72004856", "Capital": 14520.0}, "30840213": {"Category": ["藥品", "食品"], "SubCate": {"藥品製造": ["人用西藥製造"], "食品批發": ["未分類其他食品批發"], "藥品零售": ["西藥零售"], "藥品批發": ["西藥批發"]}, "Risk": "1", "ComName": "人人化學製藥股份有限公司", "Amount": "5.0967319", "Uninum": "30840213", "Capital": 3000.0}, "75031602": {"Category": ["藥品", "其他", "飲料"], "SubCate": {"藥品製造": ["人用西藥製造"], "其他批發": ["其他化粧品批發", "其他清潔用品批發"], "飲料零售": ["飲料零售"]}, "Risk": "1", "ComName": "三洋藥品工業股份有限公司", "Amount": "0.0095388", "Uninum": "75031602", "Capital": 151800.0}, "89283375": {"Category": ["藥品", "食品", "飼料"], "SubCate": {"食品批發": ["未分類其他食品批發"], "藥品批發": ["動物藥品批發", "西藥批發"], "動物飼料批發": ["動物飼料批發"]}, "Risk": "3", "ComName": "衛采製藥股份有限公司", "Amount": "0.0009709", "Uninum": "89283375", "Capital": 27000.0}, "84149006": {"Category": ["藥品", "其他"], "SubCate": {"藥品製造": ["生物藥品製造", "人用西藥製造"], "其他批發": ["其他商品經紀"], "藥品批發": ["西藥批發"]}, "Risk": "2", "ComName": "健亞生物科技股份有限公司", "Amount": "0.1131423", "Uninum": "84149006", "Capital": 100806.0}, "69601921": {"Category": ["化學", "藥品", "其他"], "SubCate": {"其他批發": ["實驗設備批發"], "藥品批發": ["其他藥品及醫療用品批發"], "其他零售": ["未分類其他綜合商品零售"], "化學批發": ["其他化學製品批發"]}, "Risk": "1", "ComName": "新芳良化工原料儀器有限公司", "Amount": "0.0925800", "Uninum": "69601921", "Capital": 1000.0}, "53599548": {"Category": ["飼料", "其他", "農產"], "SubCate": {"其他批發": ["其他商品經紀"], "動物飼料製造": ["動物飼料配製"], "農產栽培": ["其他特用作物栽培"], "動物飼料批發": ["動物飼料批發"]}, "Risk": "3", "ComName": "那米亞發酵股份有限公司", "Amount": "0.0073300", "Uninum": "53599548", "Capital": 5000.0}, "22418450": {"Category": ["化學"], "SubCate": {"化學製造": ["未分類其他化學製品製造", "清潔劑製造"]}, "Risk": "2", "ComName": "乘立化學工業股份有限公司", "Amount": "38.8550000", "Uninum": "22418450", "Capital": 500.0}, "54170142": {"Category": ["藥品", "其他"], "SubCate": {"藥品零售": ["西藥零售"], "其他產業": ["自然及工程科學研究發展服務"]}, "Risk": "2", "ComName": "醣基生醫股份有限公司", "Amount": "1.2900070", "Uninum": "54170142", "Capital": 180000.0}, "11026506": {"Category": ["其他"], "SubCate": {"其他製造": ["電線及電纜製造", "木質容器製造", "合板及組合木材製造"], "其他產業": ["報關服務"]}, "Risk": "1", "ComName": "大同股份有限公司", "Amount": "0.0015457", "Uninum": "11026506", "Capital": 4549527.0}, "53251906": {"Category": ["化學", "食品"], "SubCate": {"食品製造": ["其他未分類食品製造"], "化學製造": ["其他化粧品製造"]}, "Risk": "2", "ComName": "京宸生醫科技有限公司", "Amount": "44.5300000", "Uninum": "53251906", "Capital": 1600.0}, "22067757": {"Category": ["化學", "其他", "食品"], "SubCate": {"其他批發": ["其他清潔用品批發"], "食品批發": ["未分類其他食品批發"], "化學批發": ["其他化學製品批發"]}, "Risk": "2", "ComName": "今冠化工股份有限公司", "Amount": "3.1200000", "Uninum": "22067757", "Capital": 500.0}, "16766281": {"Category": ["藥品", "食品"], "SubCate": {"藥品製造": ["人用西藥製造"], "食品批發": ["保健食品批發"], "藥品零售": ["西藥零售"], "藥品批發": ["西藥批發"]}, "Risk": "3", "ComName": "懷特新藥科技股份有限公司", "Amount": "0.0106000", "Uninum": "16766281", "Capital": 163616.0}, "58003103": {"Category": ["藥品", "其他", "食品"], "SubCate": {"藥品製造": ["人用西藥製造"], "其他批發": ["其他化粧品批發"], "食品批發": ["未分類其他食品批發"], "藥品批發": ["西藥批發"]}, "Risk": "1", "ComName": "人生製藥股份有限公司", "Amount": "0.3068923", "Uninum": "58003103", "Capital": 7500.0}, "66372059": {"Category": ["藥品", "其他", "食品"], "SubCate": {"藥品製造": ["中藥製造", "人用西藥製造"], "其他製造": ["其他醫療器材及用品製造"], "食品批發": ["未分類其他食品批發"]}, "Risk": "1", "ComName": "德山製藥股份有限公司", "Amount": "0.0008448", "Uninum": "66372059", "Capital": 6000.0}, "03787101": {"Category": ["其他", "食品", "飲料"], "SubCate": {"其他製造": ["菸草製造"], "其他批發": ["其他商品經紀"], "食品批發": ["未分類其他食品批發"], "飲料製造": ["其他酒精飲料製造"]}, "Risk": "3", "ComName": "臺灣菸酒股份有限公司", "Amount": "0.0439655", "Uninum": "03787101", "Capital": 4385499.0}, "69275313": {"Category": ["其他"], "SubCate": {"其他批發": ["綜合商品批發"]}, "Risk": "2", "ComName": "南光化學製藥股份有限公司", "Amount": "0.0734165", "Uninum": "69275313", "Capital": 89962.0}, "23443294": {"Category": ["藥品", "飼料"], "SubCate": {"藥品批發": ["其他藥品及醫療用品批發", "中藥批發"], "動物飼料批發": ["動物飼料批發"]}, "Risk": "1", "ComName": "登盛企業股份有限公司", "Amount": "0.0053200", "Uninum": "23443294", "Capital": 2800.0}, "71078598": {"Category": ["藥品", "食品"], "SubCate": {"藥品製造": ["人用西藥製造"], "食品製造": ["其他未分類食品製造"], "藥品零售": ["西藥零售"], "藥品批發": ["中藥批發"]}, "Risk": "2", "ComName": "仙台藥品工業股份有限公司", "Amount": "0.0005124", "Uninum": "71078598", "Capital": 6000.0}, "11920905": {"Category": ["藥品"], "SubCate": {"藥品製造": ["人用西藥製造", "人用西藥製造"]}, "Risk": "2", "ComName": "台灣田邊製藥股份有限公司", "Amount": "0.0044170", "Uninum": "11920905", "Capital": 9000.0}, "55119262": {"Category": ["食品"], "SubCate": {"食品製造": ["食品罐頭（肉類、水產、蔬果罐頭除外）製造", "蔬果罐頭製造", "水產罐頭製造"]}, "Risk": "1", "ComName": "佳美食品工業股份有限公司", "Amount": "1.0280000", "Uninum": "55119262", "Capital": 3000.0}, "90250035": {"Category": ["藥品", "食品"], "SubCate": {"藥品製造": ["中藥製造", "人用西藥製造"], "食品製造": ["特殊營養食品製造"]}, "Risk": "1", "ComName": "台灣陽生製藥工業股份有限公司", "Amount": "0.0014650", "Uninum": "90250035", "Capital": 5100.0}, "22102473": {"Category": ["飲料", "食品"], "SubCate": {"食品製造": ["其他未分類食品製造"], "飲料製造": ["其他乳品製造"], "食品零售": ["罐頭食品零售"]}, "Risk": "1", "ComName": "佳格食品股份有限公司", "Amount": "0.0003310", "Uninum": "22102473", "Capital": 792697.0}, "28623865": {"Category": ["藥品", "其他"], "SubCate": {"藥品製造": ["中藥製造"], "藥品零售": ["西藥零售"], "其他產業": ["未分類其他技術檢測及分析服務"], "藥品批發": ["西藥批發"]}, "Risk": "2", "ComName": "台灣漢藥生技股份有限公司", "Amount": "0.0053060", "Uninum": "28623865", "Capital": 10000.0}, "85615014": {"Category": ["藥品"], "SubCate": {"藥品製造": ["人用西藥製造"]}, "Risk": "1", "ComName": "臺灣汎生製藥廠股份有限公司", "Amount": "0.1374196", "Uninum": "85615014", "Capital": 28115.0}, "23004605": {"Category": ["飲料"], "SubCate": {"飲料批發": ["茶葉批發"]}, "Risk": "1", "ComName": "英橋企業股份有限公司", "Amount": "0.0003244", "Uninum": "23004605", "Capital": 800.0}, "20906783": {"Category": ["農產"], "SubCate": {"農產批發": ["未分類其他農產原料批發"]}, "Risk": "1", "ComName": "遠東藍藻工業股份有限公司屏東工廠", "Amount": "0.0044250", "Uninum": "20906783", "Capital": 5000.0}, "80280616": {"Category": ["其他"], "SubCate": {"其他產業": ["自然及工程科學研究發展服務"]}, "Risk": "1", "ComName": "國鼎生物科技股份有限公司", "Amount": "0.1008215", "Uninum": "80280616", "Capital": 88019.0}, "18791960": {"Category": ["藥品", "其他", "飼料"], "SubCate": {"其他批發": ["電子器材、電子設備批發"], "藥品批發": ["動物藥品批發"], "動物飼料批發": ["動物飼料批發"]}, "Risk": "3", "ComName": "建盈股份有限公司", "Amount": "0.0073748", "Uninum": "18791960", "Capital": 7000.0}, "53096433": {"Category": ["藥品", "其他"], "SubCate": {"藥品製造": ["人用西藥製造"], "其他製造": ["其他醫療器材及用品製造"], "藥品批發": ["西藥批發"], "其他零售": ["其他化粧品零售"]}, "Risk": "1", "ComName": "歐帕生技醫藥股份有限公司", "Amount": "0.0355038", "Uninum": "53096433", "Capital": 40000.0}, "42042734": {"Category": ["化學", "藥品", "食品"], "SubCate": {"藥品製造": ["人用西藥製造"], "食品製造": ["特殊營養食品製造"], "藥品零售": ["西藥零售"], "化學製造": ["其他化粧品製造"]}, "Risk": "3", "ComName": "杏輝藥品工業股份有限公司", "Amount": "0.7138149", "Uninum": "42042734", "Capital": 161271.0}, "04883172": {"Category": ["化學", "藥品", "其他"], "SubCate": {"藥品製造": ["人用西藥製造"], "其他批發": ["其他商品經紀"], "化學製造": ["其他化粧品製造"]}, "Risk": "2", "ComName": "中生生技製藥股份有限公司", "Amount": "0.0058350", "Uninum": "04883172", "Capital": 7000.0}, "58090015": {"Category": ["化學", "藥品", "其他"], "SubCate": {"藥品製造": ["中藥製造", "人用西藥製造"], "其他產業": ["其他管理顧問服務"], "化學製造": ["其他化粧品製造"]}, "Risk": "1", "ComName": "中美兄弟製藥股份有限公司", "Amount": "0.0202439", "Uninum": "58090015", "Capital": 10000.0}, "11347802": {"Category": ["飲料", "其他", "食品", "農產"], "SubCate": {"食品製造": ["味精製造"], "飲料製造": ["其他非酒精飲料製造"], "其他批發": ["其他商品經紀"], "農產栽培": ["未分類其他畜牧"]}, "Risk": "1", "ComName": "味全食品工業股份有限公司", "Amount": "0.0001413", "Uninum": "11347802", "Capital": 600000.0}, "16130471": {"Category": ["化學", "藥品", "食品", "飼料"], "SubCate": {"藥品製造": ["人用西藥製造"], "食品製造": ["其他未分類食品製造"], "動物飼料製造": ["動物飼料配製"], "化學製造": ["其他肥料製造"]}, "Risk": "1", "ComName": "生展生物科技股份有限公司", "Amount": "0.0007378", "Uninum": "16130471", "Capital": 18559.0}, "50531334": {"Category": ["化學", "其他"], "SubCate": {"其他批發": ["其他電子設備及其零組件批發"], "化學製造": ["其他基本化學材料製造"], "化學批發": ["化學溶劑、工業添加劑批發", "其他化學原料批發"]}, "Risk": "2", "ComName": "景明化工股份有限公司", "Amount": "309.7142643", "Uninum": "50531334", "Capital": 8000.0}, "20780031": {"Category": ["化學"], "SubCate": {"化學批發": ["其他化學原料批發"]}, "Risk": "2", "ComName": "及福企業有限公司", "Amount": "62.5400000", "Uninum": "20780031", "Capital": 230.0}, "18930007": {"Category": ["藥品"], "SubCate": {"藥品批發": ["中藥批發"]}, "Risk": "1", "ComName": "勝昌製藥廠股份有限公司", "Amount": "0.0290796", "Uninum": "18930007", "Capital": 36000.0}, "03235804": {"Category": ["化學", "其他"], "SubCate": {"其他批發": ["電子器材、電子設備批發"], "化學批發": ["化學溶劑、工業添加劑批發", "染料、顏料批發", "其他化學原料批發"]}, "Risk": "3", "ComName": "東芳貿易股份有限公司", "Amount": "56.4700000", "Uninum": "03235804", "Capital": 15048.0}, "23415179": {"Category": ["藥品"], "SubCate": {"藥品製造": ["中藥製造"], "藥品零售": ["中藥零售"], "藥品批發": ["中藥批發"]}, "Risk": "3", "ComName": "仙豐股份有限公司", "Amount": "0.0159200", "Uninum": "23415179", "Capital": 25000.0}, "43199950": {"Category": ["藥品"], "SubCate": {"藥品製造": ["中藥製造", "人用西藥製造"], "藥品批發": ["其他藥品及醫療用品批發"]}, "Risk": "2", "ComName": "健喬信元醫藥生技股份有限公司", "Amount": "85.5592870", "Uninum": "43199950", "Capital": 131606.0}, "13056907": {"Category": ["藥品", "其他"], "SubCate": {"藥品製造": ["生物藥品製造"], "其他製造": ["其他醫療器材及用品製造"], "其他批發": ["其他化粧品批發"], "其他零售": ["其他化粧品零售"]}, "Risk": "1", "ComName": "儕陞生化技術股份有限公司", "Amount": "0.0010007", "Uninum": "13056907", "Capital": 52715.0}, "22243543": {"Category": ["化學", "藥品", "食品"], "SubCate": {"藥品製造": ["中藥製造"], "食品製造": ["特殊營養食品製造", "奶粉製造"], "化學製造": ["其他化粧品製造"]}, "Risk": "1", "ComName": "科達製藥股份有限公司", "Amount": "0.0072068", "Uninum": "22243543", "Capital": 25000.0}, "22868808": {"Category": ["食品"], "SubCate": {"食品製造": ["其他調味品製造"]}, "Risk": "2", "ComName": "廣福林有限公司", "Amount": "0.0001786", "Uninum": "22868808", "Capital": 2900.0}, "28163834": {"Category": ["藥品", "飲料"], "SubCate": {"藥品製造": ["生物藥品製造"], "飲料製造": ["其他非酒精飲料製造", "咖啡粉製造"], "藥品零售": ["西藥零售"]}, "Risk": "2", "ComName": "光南製藥股份有限公司", "Amount": "0.0003178", "Uninum": "28163834", "Capital": 1320.0}, "69811927": {"Category": ["藥品", "飲料", "食品"], "SubCate": {"藥品製造": ["中藥製造"], "食品製造": ["其他未分類食品製造"], "飲料製造": ["其他非酒精飲料製造"], "藥品零售": ["中藥零售"]}, "Risk": "2", "ComName": "天一藥廠股份有限公司", "Amount": "0.0008520", "Uninum": "69811927", "Capital": 15500.0}, "13187561": {"Category": ["食品", "農產"], "SubCate": {"食品批發": ["冷凍調理食品批發", "水果批發", "蔬菜批發"], "農產栽培": ["其他農作物栽培"]}, "Risk": "2", "ComName": "宏偉冷凍食品股份有限公司", "Amount": "0.7962860", "Uninum": "13187561", "Capital": 15000.0}, "28060387": {"Category": ["其他", "食品"], "SubCate": {"其他批發": ["其他化粧品批發"], "食品批發": ["未分類其他食品批發"]}, "Risk": "3", "ComName": "明文彥科技有限公司", "Amount": "0.0013200", "Uninum": "28060387", "Capital": 500.0}, "84299742": {"Category": ["藥品"], "SubCate": {"藥品製造": ["人用西藥製造"], "藥品批發": ["動物藥品批發", "西藥批發"]}, "Risk": "3", "ComName": "聯亞生技開發股份有限公司", "Amount": "2.3097699", "Uninum": "84299742", "Capital": 84800.0}, "12765162": {"Category": ["其他"], "SubCate": {"其他零售": ["未分類其他全新商品零售", "電腦及電腦週邊設備零售", "未分類其他家庭器具及用品零售", "其他家庭電器零售"]}, "Risk": "1", "ComName": "豐常實業有限公司", "Amount": "0.4544067", "Uninum": "12765162", "Capital": 350.0}, "58176511": {"Category": ["化學", "其他", "飲料"], "SubCate": {"其他製造": ["金屬罐製造", "塑膠皮、塑膠布製造"], "飲料製造": ["其他乳品製造"], "化學製造": ["其他基本化學材料製造"]}, "Risk": "2", "ComName": "宏全國際股份有限公司台中廠", "Amount": "15.5200000", "Uninum": "58176511", "Capital": 309847.0}, "22225186": {"Category": ["其他"], "SubCate": {"其他批發": ["其他未分類專賣批發"]}, "Risk": "2", "ComName": "政星企業有限公司", "Amount": "15.1280000", "Uninum": "22225186", "Capital": 1500.0}, "44988454": {"Category": ["化學", "藥品", "飲料", "食品"], "SubCate": {"藥品製造": ["動物用西藥製造"], "食品製造": ["其他未分類食品製造"], "飲料製造": ["其他非酒精飲料製造"], "化學製造": ["清潔劑製造"]}, "Risk": "2", "ComName": "優良化學製藥股份有限公司", "Amount": "0.0065051", "Uninum": "44988454", "Capital": 65000.0}, "68336642": {"Category": ["藥品", "食品"], "SubCate": {"藥品製造": ["中藥製造"], "食品批發": ["未分類其他食品批發"], "藥品零售": ["中藥零售"], "藥品批發": ["中藥批發"]}, "Risk": "1", "ComName": "東陽製藥股份有限公司", "Amount": "0.0014850", "Uninum": "68336642", "Capital": 2700.0}, "16894172": {"Category": ["其他"], "SubCate": {"其他批發": ["其他未分類專賣批發"]}, "Risk": "2", "ComName": "友和貿易股份有限公司", "Amount": "456.6485585", "Uninum": "16894172", "Capital": 16043.0}, "23625631": {"Category": ["藥品", "其他", "食品"], "SubCate": {"食品批發": ["未分類其他食品批發"], "其他產業": ["自然及工程科學研究發展服務"], "藥品批發": ["西藥批發"], "食品零售": ["未分類其他食品及飲料、菸草製品零售"]}, "Risk": "2", "ComName": "遠東生物科技股份有限公司", "Amount": "0.0073040", "Uninum": "23625631", "Capital": 15600.0}, "47154259": {"Category": ["化學", "藥品", "其他"], "SubCate": {"藥品製造": ["人用西藥製造"], "其他批發": ["醫療機械設備批發"], "化學製造": ["其他化粧品製造"]}, "Risk": "2", "ComName": "濟生化學製藥廠股份有限公司", "Amount": "0.0016656", "Uninum": "47154259", "Capital": 56982.0}, "84947629": {"Category": ["食品"], "SubCate": {"食品製造": ["食用植物油製造"], "食品批發": ["調味料（辛、香料除外）批發", "食用油脂批發"], "食品零售": ["未分類其他食品及飲料、菸草製品零售"]}, "Risk": "2", "ComName": "維義事業股份有限公司", "Amount": "0.0052800", "Uninum": "84947629", "Capital": 15000.0}, "23045916": {"Category": ["藥品", "其他"], "SubCate": {"藥品製造": ["人用西藥製造"], "其他批發": ["其他化粧品批發", "綜合商品批發"]}, "Risk": "2", "ComName": "瑞安大藥廠股份有限公司", "Amount": "7.1376443", "Uninum": "23045916", "Capital": 34955.0}, "84476394": {"Category": ["其他", "食品", "農產"], "SubCate": {"農產批發": ["豆類、麥類及其他雜糧批發"], "其他產業": ["行銷管理顧問服務", "未分類其他餐飲"], "食品製造": ["其他未分類食品製造"]}, "Risk": "2", "ComName": "長榮空廚股份有限公司", "Amount": "0.0412400", "Uninum": "84476394", "Capital": 100000.0}, "80499901": {"Category": ["藥品", "其他", "食品"], "SubCate": {"食品製造": ["其他未分類食品製造"], "其他產業": ["雜誌（期刊）出版"], "藥品批發": ["西藥批發"]}, "Risk": "1", "ComName": "躍欣生技醫藥股份有限公司", "Amount": "0.9815303", "Uninum": "80499901", "Capital": 42000.0}, "84153872": {"Category": ["化學", "食品"], "SubCate": {"食品零售": ["未分類其他食品及飲料、菸草製品零售"], "食品批發": ["未分類其他食品批發"], "化學批發": ["其他化學製品批發"]}, "Risk": "2", "ComName": "明韻有限公司", "Amount": "85.3300000", "Uninum": "84153872", "Capital": 500.0}, "03707901": {"Category": ["其他"], "SubCate": {"其他製造": ["汽油製造"], "其他產業": ["氣體燃料供應"], "其他零售": ["汽油零售", "直營連鎖式便利商店"]}, "Risk": "1", "ComName": "台灣中油股份有限公司", "Amount": "24.7900167", "Uninum": "03707901", "Capital": 13010000.0}, "87972868": {"Category": ["飲料"], "SubCate": {"飲料製造": ["其他酒精飲料製造"], "飲料批發": ["國產菸酒批發"], "飲料零售": ["飲料零售", "菸酒零售"]}, "Risk": "2", "ComName": "臺灣菸酒股份有限公司嘉義酒廠", "Amount": "0.0065170", "Uninum": "87972868", "Capital": 0.0}}